{"$A$": ["$[-]$", "cal", [0, 5], 2.032, 0, [2.0315617122898058]], "$B$": ["$[-]$", "cal", [0, 2], 0.545, 0, [0.5449887954060443]], "$C$": ["$[dB]$", "cal", [-30, -5], -15.799, 0, [-15.798632272785877]], "$D$": ["$[dB m^3/m^3]$", "cal", [10, 100], 30.048, 0, [30.048363352022964]], "$W_{fc}$": ["$[m^3/m^3]$", "fix", ["/", "/"], 0.35, "/"], "$W_w$": ["$[m^3/m^3]$", "fix", ["/", "/"], 0.12, "/"], "$\\rho_{st}$": ["$[mm/h]$", "fix", ["/", "/"], 0.6, "/"], "$K_{c0}$": ["$[-]$", "cal", [0, 1], 0.33, 0, [0.33032110838546913]], "$\\alpha$": ["$[-]$", "cal", [1, 10], 1.0, 0, [1.0]]}